multipoles/__init__.py
multipoles/expansion.py
multipoles-0.4.1.dist-info/LICENSE
multipoles-0.4.1.dist-info/METADATA
multipoles-0.4.1.dist-info/WHEEL
multipoles-0.4.1.dist-info/top_level.txt
multipoles-0.4.1.dist-info/RECORD
