Metadata-Version: 2.1
Name: multipoles
Version: 0.4.1
Summary: A Python package for multipole expansions of electrostatic or gravitational potentials
Author: Matthias Baer
Maintainer-email: Matthias Baer <matthias.r.baer@googlemail.com>
License: MIT
Project-URL: Homepage, https://github.com/maroba/multipoles
Project-URL: source, https://github.com/maroba/multipoles
Project-URL: Issues, https://github.com/maroba/multipoles/issues
Project-URL: tracker, https://github.com/maroba/multipoles/issues
Keywords: multipole expansion,physics,scientific-computing
Classifier: Programming Language :: Python :: 3
Classifier: Programming Language :: Python :: 3.8
Classifier: Programming Language :: Python :: 3.9
Classifier: Programming Language :: Python :: 3.10
Classifier: Programming Language :: Python :: 3.11
Classifier: Programming Language :: Python :: 3.12
Classifier: Intended Audience :: Developers
Classifier: Topic :: Scientific/Engineering :: Mathematics
Classifier: License :: OSI Approved :: MIT License
Classifier: Operating System :: OS Independent
Requires-Python: >=3.8
License-File: LICENSE
Requires-Dist: numpy
Requires-Dist: scipy
